setup.py
django_hash_password/__init__.py
django_hash_password.egg-info/PKG-INFO
django_hash_password.egg-info/SOURCES.txt
django_hash_password.egg-info/dependency_links.txt
django_hash_password.egg-info/top_level.txt
django_hash_password.egg-info/zip-safe
django_hash_password/management/__init__.py
django_hash_password/management/commands/__init__.py
django_hash_password/management/commands/hash_password.py