Metadata-Version: 1.1
Name: django-hash-password
Version: 0.0.1
Summary: Generate hashed passwords.
Home-page: https://github.com/kelonye/django-hash-password
Author: Mitchel Kelonye
Author-email: kelonyemitchel@gmail.com
License: MIT License
Platform: UNKNOWN
Requires: Django (>=1.3.0)
